{
    "type": "minecraft:smithing_transform",
    "template": "minecraft:rib_armor_trim_smithing_template",
    "base": "minecraft:golden_shovel",
    "addition": "minecraft:amethyst_shard",
    "result": {
        "id": "minecraft:golden_shovel",
        "components": {
            "minecraft:item_model": "katzteam:golden_shovel_rib_amethyst",
            "minecraft:trim": {
                "material": "minecraft:amethyst",
                "pattern": "minecraft:rib",
                "show_in_tooltip": true
            }
        }
    }
}