{
    "type": "minecraft:smithing_transform",
    "template": "minecraft:wayfinder_armor_trim_smithing_template",
    "base": "minecraft:wooden_shovel",
    "addition": "minecraft:emerald",
    "result": {
        "id": "minecraft:wooden_shovel",
        "components": {
            "minecraft:item_model": "katzteam:wooden_shovel_wayfinder_emerald",
            "minecraft:trim": {
                "material": "minecraft:emerald",
                "pattern": "minecraft:wayfinder",
                "show_in_tooltip": true
            }
        }
    }
}